Metadata-Version: 1.0
Name: MyPackage0406019
Version: 1.1
Summary: Math functions
Home-page: UNKNOWN
Author: UNKNOWN
Author-email: UNKNOWN
License: UNKNOWN
Platform: UNKNOWN
